djajax/__init__.py
djajax/__version__.py
djajax/apps.py
djajax/fast_test_runner.py
djajax/http.py
djajax/models.py
djajax/views.py
djajax/static/js/djajax.js
djajax/templatetags/__init__.py
djajax/templatetags/djajax.py
djajax/tests/__init__.py
djajax/tests/test_serializable_mixin.py
djajax-0.0.4.dist-info/METADATA
djajax-0.0.4.dist-info/RECORD
djajax-0.0.4.dist-info/WHEEL
djajax-0.0.4.dist-info/top_level.txt
