Metadata-Version: 2.1
Name: djajax
Version: 0.0.4
Summary: Helper utilities for working with Ajax in Django
Home-page: https://github.com/adamghill/djajax
Author: Adam Hill
Author-email: adamghill@yahoo.com
License: MIT
Platform: UNKNOWN
Classifier: License :: OSI Approved :: MIT License
Classifier: Programming Language :: Python
Classifier: Programming Language :: Python :: 2.7
Classifier: Programming Language :: Python :: Implementation :: CPython
Classifier: Programming Language :: Python :: Implementation :: PyPy
Requires-Dist: Django
